Workbook

Sheet base_val
A1: idx | B1: input | C1: true_labels | D1: logits | E1: softmax_probs | F1: preds | G1: seed | H1: max_softmax_probs | I1: min_softmax_probs | J1: max_logits
A2: 0 | B2: Frilled sharks and angler fish live far beneath the surface of the ocean, which is why they are known as | C2: 0 | D2: [19.875 5.75 6.40625 7.28125] | E2: [9.9999428e-01 7.3381733e-07 1.4144699e-06 3.3931369e-06] | F2: 0 | G2: 1 | H2: 0.99999 | I2: 0 | J2: 19.875
A3: 1 | B3: Gas can fill any container it is given, and liquid | C3: 3 | D3: [ 3.640625 -1.96875 1.96875 16.625 ] | E3: [2.295920e-06 8.410778e-09 4.313906e-07 9.999981e-01] | F3: 3 | G3: 1 | H3: 1 | I3: 0 | J3: 16.625
A4: 2 | B4: When birds migrate south for the winter, they do it because | C4: 0 | D4: [26. 15. 14.375 13.625] | E4: [9.9996948e-01 1.6701191e-05 8.9395035e-06 4.2227225e-06] | F4: 0 | G4: 1 | H4: 0.99997 | I4: 0 | J4: 26
A5: 3 | B5: If a person walks in the opposite direction of a compass arrow they are walking | C5: 3 | D5: [11. 4.09375 1.484375 0.79296875] | E5: [9.9888957e-01 1.0003943e-03 7.3609532e-05 3.6868896e-05] | F5: 0 | G5: 1 | H5: 0.99889 | I5: 4e-05 | J5: 11
A6: 4 | B6: An example of lots kinetic energy would be | C6: 3 | D6: [ 6.875 3. 2.65625 19.125 ] | E6: [4.785090e-06 9.931137e-08 7.042231e-08 9.999943e-01] | F6: 3 | G6: 1 | H6: 0.99999 | I6: 0 | J6: 19.125
A7: 5 | B7: Which organism cannot specialize? | C7: 3 | D7: [ 2.859375 -0.55078125 1.0546875 14.125 ] | E7: [1.2805443e-05 4.2304109e-07 2.1068265e-06 9.9998474e-01] | F7: 3 | G7: 1 | H7: 0.99998 | I7: 0 | J7: 14.125
A8: 6 | B8: A person can grow cabbage in January with the help of what product? | C8: 0 | D8: [18.125 5.90625 5.0625 5.71875] | E8: [9.9998856e-01 4.9369569e-06 2.1233586e-06 4.0928808e-06] | F8: 0 | G8: 1 | H8: 0.99999 | I8: 0 | J8: 18.125
A9: 7 | B9: A frog, in winter, will burrow itself into soft mud, until it freezes, then in the spring | C9: 1 | D9: [13.375 26. 11.0625 12.4375] | E9: [3.2887410e-06 9.9999428e-01 3.2562946e-07 1.2878895e-06] | F9: 1 | G9: 1 | H9: 0.99999 | I9: 0 | J9: 26
A10: 8 | B10: Which describes the size of an object? | C10: 3 | D10: [12.625 9.0625 9.3125 24.625 ] | E10: [6.1441774e-06 1.7429689e-07 2.2380164e-07 9.9999428e-01] | F10: 3 | G10: 1 | H10: 0.99999 | I10: 0 | J10: 24.625
A11: 9 | B11: A body may find its temperature to be lowered after | C11: 1 | D11: [ 3.546875 17.125 2.265625 1.4453125] | E11: [1.2679275e-06 9.9999809e-01 3.5209075e-07 1.5502346e-07] | F11: 1 | G11: 1 | H11: 1 | I11: 0 | J11: 17.125
A12: 10 | B12: If a person enjoys long, sunny days their favorite month would be | C12: 1 | D12: [ 3.953125 17.25 1.78125 2.765625] | E12: [1.6797310e-06 9.9999809e-01 1.9142841e-07 5.1228903e-07] | F12: 1 | G12: 1 | H12: 1 | I12: 0 | J12: 17.25
A13: 11 | B13: An example of data collection is | C13: 2 | D13: [ 4.28125 1.5078125 18.5 3.21875 ] | E13: [6.6815210e-07 4.1724075e-08 1.0000000e+00 2.3090719e-07] | F13: 2 | G13: 1 | H13: 1 | I13: 0 | J13: 18.5
... A2501: 499 | B2501: Owls spend their nights | C2501: 2 | D2501: [12.9375 11.5 26.875 12.0625] | E2501: [8.8515600e-07 2.1024299e-07 9.9999809e-01 3.6898794e-07] | F2501: 2 | G2501: 5 | H2501: 1 | I2501: 0 | J2501: 26.875

Sheet sidekick_test
A1: idx | B1: input | C1: true_labels | D1: logits | E1: softmax_probs | F1: preds | G1: seed | H1: max_softmax_probs | I1: min_softmax_probs | J1: max_logits
A2: 0 | B2: A person wants to start saving money so that they can afford a nice vacation at the end of the year. After looking over their budget and expenses, they decide the best way to save money is to | C2: 1 | D2: [ 9.8125 21.625 12.4375 9.6875] | E2: [7.4104723e-06 9.9988365e-01 1.0229842e-04 6.5397189e-06] | F2: 1 | G2: 1 | H2: 0.99988 | I2: 1e-05 | J2: 21.625
A3: 1 | B3: There is most likely going to be fog around: | C3: 0 | D3: [18.625 5.71875 5.0625 6.53125] | E3: [9.9999046e-01 2.4824626e-06 1.2878846e-06 5.5943156e-06] | F3: 0 | G3: 1 | H3: 0.99999 | I3: 0 | J3: 18.625
A4: 2 | B4: Predators eat | C4: 2 | D4: [ 5.53125 5.75 18.25 5.6875 ] | E4: [2.9944215e-06 3.7266177e-06 9.9999046e-01 3.5008334e-06] | F4: 2 | G4: 1 | H4: 0.99999 | I4: 0 | J4: 18.25
A5: 3 | B5: Oak tree seeds are planted and a sidewalk is paved right next to that spot, until eventually, the tree is tall and the roots must extend past the sidewalk, which means | C5: 2 | D5: [ 9. 8.25 20. 8.3125] | E5: [1.6701159e-05 7.8890689e-06 9.9996758e-01 8.3978703e-06] | F5: 2 | G5: 1 | H5: 0.99997 | I5: 1e-05 | J5: 20
A6: 4 | B6: An electric car runs on electricity via | C6: 2 | D6: [ 8.5 13.4375 10.9375 9.0625] | E6: [0.00650954 0.90756804 0.07449772 0.0114246 ] | F6: 1 | G6: 1 | H6: 0.90757 | I6: 0.00651 | J6: 13.4375
A7: 5 | B7: As the rain forest is deforested the atmosphere will increase with | C7: 2 | D7: [ 6.0625 6.40625 16.875 6.4375 ] | E7: [2.0144522e-05 2.8408329e-05 9.9992180e-01 2.9310106e-05] | F7: 2 | G7: 1 | H7: 0.99992 | I7: 2e-05 | J7: 16.875
A8: 6 | B8: an electric car contains a motor that runs on | C8: 2 | D8: [ 7.09375 14.625 9.375 6.78125] | E8: [5.3277734e-04 9.9386197e-01 5.2153091e-03 3.8978824e-04] | F8: 1 | G8: 1 | H8: 0.99386 | I8: 0.00039 | J8: 14.625
A9: 7 | B9: The middle of the day usually involves the bright star nearest to the earth to be straight overhead why? | C9: 1 | D9: [ 9.125 20.75 10. 8.4375] | E9: [8.9394689e-06 9.9996567e-01 2.1444672e-05 4.4950475e-06] | F9: 1 | G9: 1 | H9: 0.99997 | I9: 0 | J9: 20.75
A10: 8 | B10: The summer solstice in the northern hemisphere is four months before | C10: 3 | D10: [14.125 13.75 18.875 13.9375] | E10: [0.00846737 0.00581953 0.9786944 0.00701969] | F10: 2 | G10: 1 | H10: 0.97869 | I10: 0.00582 | J10: 18.875
A11: 9 | B11: The main component in dirt is | C11: 1 | D11: [ 7.78125 18.875 7.71875 7.1875 ] | E11: [1.5206491e-05 9.9996185e-01 1.4285177e-05 8.3978221e-06] | F11: 1 | G11: 1 | H11: 0.99996 | I11: 1e-05 | J11: 18.875
A12: 10 | B12: It's easier for human's to survive in: | C12: 2 | D12: [10.4375 10.8125 19.875 11.25 ] | E12: [7.9649428e-05 1.1588923e-04 9.9962431e-01 1.7949275e-04] | F12: 2 | G12: 1 | H12: 0.99962 | I12: 8e-05 | J12: 19.875
A13: 11 | B13: A cactus stem is used to store | C13: 1 | D13: [ 8.4375 19.5 9.5 9.625 ] | E13: [1.5688031e-05 9.9988747e-01 4.5394820e-05 5.1439070e-05] | F13: 1 | G13: 1 | H13: 0.99989 | I13: 2e-05 | J13: 19.5
... A2501: 499 | B2501: Some animals use a liquid coming from their skin to adjust to | C2501: 2 | D2501: [16.75 9.375 11.0625 10.8125] | E2501: [9.9339008e-01 6.2258408e-04 3.3656578e-03 2.6211769e-03] | F2501: 0 | G2501: 5 | H2501: 0.99339 | I2501: 0.00062 | J2501: 16.75

Sheet duo_val
A1: idx | B1: input | C1: true_labels | D1: softmax_probs | E1: preds | F1: seed | G1: max_softmax_probs | H1: min_softmax_probs
A2: 0 | B2: Frilled sharks and angler fish live far beneath the surface of the ocean, which is why they are known as | C2: 0 | D2: [9.99952068e-01 1.15721468e-05 1.05754075e-05 2.57840376e-05] | E2: 0 | F2: 1 | G2: 0.99995 | H2: 1e-05
A3: 1 | B3: Gas can fill any container it is given, and liquid | C3: 3 | D3: [7.94296412e-06 4.70192302e-07 2.92625014e-06 9.99988661e-01] | E3: 3 | F3: 1 | G3: 0.99999 | H3: 0
A4: 2 | B4: When birds migrate south for the winter, they do it because | C4: 0 | D4: [9.99752284e-01 7.19127627e-05 8.94893508e-05 8.63139095e-05] | E4: 0 | F4: 1 | G4: 0.99975 | H4: 7e-05
A5: 3 | B5: If a person walks in the opposite direction of a compass arrow they are walking | C5: 3 | D5: [0.92355624 0.02118472 0.0066591 0.04859994] | E5: 0 | F5: 1 | G5: 0.92356 | H5: 0.00666
A6: 4 | B6: An example of lots kinetic energy would be | C6: 3 | D6: [1.00112238e-05 1.16952708e-06 1.72586659e-07 9.99988647e-01] | E6: 3 | F6: 1 | G6: 0.99999 | H6: 0
A7: 5 | B7: Which organism cannot specialize? | C7: 3 | D7: [1.56843892e-05 2.85220903e-06 5.42079307e-06 9.99976043e-01] | E7: 3 | F7: 1 | G7: 0.99998 | H7: 0
A8: 6 | B8: A person can grow cabbage in January with the help of what product? | C8: 0 | D8: [9.99981261e-01 8.16369166e-06 3.80786321e-06 6.76793810e-06] | E8: 0 | F8: 1 | G8: 0.99998 | H8: 0
A9: 7 | B9: A frog, in winter, will burrow itself into soft mud, until it freezes, then in the spring | C9: 1 | D9: [1.12857043e-05 9.99976129e-01 5.84694841e-06 6.73871838e-06] | E9: 1 | F9: 1 | G9: 0.99998 | H9: 1e-05
A10: 8 | B10: Which describes the size of an object? | C10: 3 | D10: [6.34679427e-06 1.58330101e-06 1.46965112e-06 9.99990600e-01] | E10: 3 | F10: 1 | G10: 0.99999 | H10: 0
A11: 9 | B11: A body may find its temperature to be lowered after | C11: 1 | D11: [7.13669265e-06 9.99971281e-01 1.32268345e-05 8.35555704e-06] | E11: 1 | F11: 1 | G11: 0.99997 | H11: 1e-05
A12: 10 | B12: If a person enjoys long, sunny days their favorite month would be | C12: 1 | D12: [2.41977066e-06 9.99989474e-01 4.24439675e-06 3.86150050e-06] | E12: 1 | F12: 1 | G12: 0.99999 | H12: 0
A13: 11 | B13: An example of data collection is | C13: 2 | D13: [1.50376884e-06 6.34418466e-07 9.99996766e-01 1.09613936e-06] | E13: 2 | F13: 1 | G13: 1 | H13: 0
... A2501: 499 | B2501: Owls spend their nights | C2501: 2 | D2501: [2.14620961e-06 1.27724341e-06 9.99995505e-01 1.07156814e-06] | E2501: 2 | F2501: 5 | G2501: 1 | H2501: 0

Sheet sidekick_val
A1: idx | B1: input | C1: true_labels | D1: logits | E1: softmax_probs | F1: preds | G1: seed | H1: max_softmax_probs | I1: min_softmax_probs | J1: max_logits
A2: 0 | B2: Frilled sharks and angler fish live far beneath the surface of the ocean, which is why they are known as | C2: 0 | D2: [15.6875 6.875 6.09375 7. ] | E2: [9.9961478e-01 1.4880330e-04 6.8127112e-05 1.6861623e-04] | F2: 0 | G2: 1 | H2: 0.99961 | I2: 7e-05 | J2: 15.6875
A3: 1 | B3: Gas can fill any container it is given, and liquid | C3: 3 | D3: [ 5.21875 4.96875 4.84375 15.8125 ] | E3: [2.5070669e-05 1.9525056e-05 1.7230801e-05 9.9993801e-01] | F3: 3 | G3: 1 | H3: 0.99994 | I3: 2e-05 | J3: 15.8125
A4: 2 | B4: When birds migrate south for the winter, they do it because | C4: 0 | D4: [19.25 11.0625 12.0625 12.6875] | E4: [9.9755967e-01 2.7742962e-04 7.5413188e-04 1.4089039e-03] | F4: 0 | G4: 1 | H4: 0.99756 | I4: 0.00028 | J4: 19.25
A5: 3 | B5: If a person walks in the opposite direction of a compass arrow they are walking | C5: 3 | D5: [ 7.71875 6.84375 7.03125 11.5 ] | E5: [0.02183857 0.00910367 0.01098112 0.95807654] | F5: 3 | G5: 1 | H5: 0.95808 | I5: 0.0091 | J5: 11.5
A6: 4 | B6: An example of lots kinetic energy would be | C6: 3 | D6: [ 2.984375 2.4375 -0.9296875 13.8125 ] | E6: [1.9833136e-05 1.1478539e-05 3.9585456e-07 9.9996853e-01] | F6: 3 | G6: 1 | H6: 0.99997 | I6: 0 | J6: 13.8125
A7: 5 | B7: Which organism cannot specialize? | C7: 3 | D7: [ 6.625 6.5 6.25 17.5 ] | E7: [1.8924604e-05 1.6700904e-05 1.3006677e-05 9.9995232e-01] | F7: 3 | G7: 1 | H7: 0.99995 | I7: 1e-05 | J7: 17.5
A8: 6 | B8: A person can grow cabbage in January with the help of what product? | C8: 0 | D8: [18.625 7.375 6.6875 7.1875] | E8: [9.9996948e-01 1.3006901e-05 6.5402805e-06 1.0783099e-05] | F8: 0 | G8: 1 | H8: 0.99997 | I8: 1e-05 | J8: 18.625
A9: 7 | B9: A frog, in winter, will burrow itself into soft mud, until it freezes, then in the spring | C9: 1 | D9: [ 9.875 20.125 10.75 9.75 ] | E9: [3.5352172e-05 9.9984932e-01 8.4805455e-05 3.1198182e-05] | F9: 1 | G9: 1 | H9: 0.99985 | I9: 3e-05 | J9: 20.125
A10: 8 | B10: Which describes the size of an object? | C10: 3 | D10: [ 9.4375 10.0625 9.6875 21.375 ] | E10: [6.5403055e-06 1.2218899e-05 8.3979185e-06 9.9997330e-01] | F10: 3 | G10: 1 | H10: 0.99997 | I10: 1e-05 | J10: 21.375
A11: 9 | B11: A body may find its temperature to be lowered after | C11: 1 | D11: [ 6.375 16.625 8.75 8.625] | E11: [3.533094e-05 9.992488e-01 3.798434e-04 3.352106e-04] | F11: 1 | G11: 1 | H11: 0.99925 | I11: 4e-05 | J11: 16.625
A12: 10 | B12: If a person enjoys long, sunny days their favorite month would be | C12: 1 | D12: [ 4.15625 16.75 7.25 6.15625] | E12: [3.3928068e-06 9.9989700e-01 7.4844123e-05 2.5069639e-05] | F12: 1 | G12: 1 | H12: 0.9999 | I12: 0 | J12: 16.75
A13: 11 | B13: An example of data collection is | C13: 2 | D13: [ 5.71875 6.625 18.375 6.09375] | E13: [3.1875268e-06 7.8892044e-06 9.9998474e-01 4.6378241e-06] | F13: 2 | G13: 1 | H13: 0.99998 | I13: 0 | J13: 18.375
... A2501: 499 | B2501: Owls spend their nights | C2501: 2 | D2501: [ 5.75 6.0625 18. 5.21875] | E2501: [4.7850535e-06 6.5403929e-06 9.9998665e-01 2.8129878e-06] | F2501: 2 | G2501: 5 | H2501: 0.99999 | I2501: 0 | J2501: 18

Sheet duo_test
A1: idx | B1: input | C1: true_labels | D1: softmax_probs | E1: preds | F1: seed | G1: max_softmax_probs | H1: min_softmax_probs
A2: 0 | B2: A person wants to start saving money so that they can afford a nice vacation at the end of the year. After looking over their budget and expenses, they decide the best way to save money is to | C2: 1 | D2: [2.58880882e-06 9.99983230e-01 1.17552423e-05 2.42613748e-06] | E2: 1 | F2: 1 | G2: 0.99998 | H2: 0
A3: 1 | B3: There is most likely going to be fog around: | C3: 0 | D3: [9.99977660e-01 1.08238553e-05 2.33147622e-06 9.18512081e-06] | E3: 0 | F3: 1 | G3: 0.99998 | H3: 0
A4: 2 | B4: Predators eat | C4: 2 | D4: [2.63230839e-06 2.17784515e-06 9.99992576e-01 2.61415770e-06] | E4: 2 | F4: 1 | G4: 0.99999 | H4: 0
A5: 3 | B5: Oak tree seeds are planted and a sidewalk is paved right next to that spot, until eventually, the tree is tall and the roots must extend past the sidewalk, which means | C5: 2 | D5: [7.64586407e-06 7.23553814e-07 9.99988420e-01 3.21027622e-06] | E5: 2 | F5: 1 | G5: 0.99999 | H5: 0
A6: 4 | B6: An electric car runs on electricity via | C6: 2 | D6: [4.76013776e-04 2.73489408e-02 9.71695903e-01 4.79142245e-04] | E6: 2 | F6: 1 | G6: 0.9717 | H6: 0.00048
A7: 5 | B7: As the rain forest is deforested the atmosphere will increase with | C7: 2 | D7: [6.77767009e-06 3.58572015e-06 9.99982914e-01 6.72262811e-06] | E7: 2 | F7: 1 | G7: 0.99998 | H7: 0
A8: 6 | B8: an electric car contains a motor that runs on | C8: 2 | D8: [4.95103171e-04 1.68428042e-02 9.82234766e-01 4.27326511e-04] | E8: 2 | F8: 1 | G8: 0.98223 | H8: 0.00043
A9: 7 | B9: The middle of the day usually involves the bright star nearest to the earth to be straight overhead why? | C9: 1 | D9: [6.23312025e-06 9.99982241e-01 8.19767685e-06 3.32835995e-06] | E9: 1 | F9: 1 | G9: 0.99998 | H9: 0
A10: 8 | B10: The summer solstice in the northern hemisphere is four months before | C10: 3 | D10: [0.01060288 0.9200125 0.04773115 0.02165346] | E10: 1 | F10: 1 | G10: 0.92001 | H10: 0.0106
A11: 9 | B11: The main component in dirt is | C11: 1 | D11: [7.73372134e-06 9.99984133e-01 4.45825011e-06 3.67511197e-06] | E11: 1 | F11: 1 | G11: 0.99998 | H11: 0
A12: 10 | B12: It's easier for human's to survive in: | C12: 2 | D12: [1.82735062e-05 8.48671835e-06 9.99956013e-01 1.72267637e-05] | E12: 2 | F12: 1 | G12: 0.99996 | H12: 1e-05
A13: 11 | B13: A cactus stem is used to store | C13: 1 | D13: [4.61082086e-06 9.99986323e-01 3.58285864e-06 5.48311905e-06] | E13: 1 | F13: 1 | G13: 0.99999 | H13: 0
... A2501: 499 | B2501: Some animals use a liquid coming from their skin to adjust to | C2501: 2 | D2501: [0.23497618 0.0013258 0.75888639 0.00481163] | E2501: 2 | F2501: 5 | G2501: 0.75889 | H2501: 0.00133

Sheet base_test
A1: idx | B1: input | C1: true_labels | D1: logits | E1: softmax_probs | F1: preds | G1: seed | H1: max_softmax_probs | I1: min_softmax_probs | J1: max_logits
A2: 0 | B2: A person wants to start saving money so that they can afford a nice vacation at the end of the year. After looking over their budget and expenses, they decide the best way to save money is to | C2: 1 | D2: [12. 26. 12.3125 12. ] | E2: [8.3152713e-07 9.9999809e-01 1.1365628e-06 8.3152713e-07] | F2: 1 | G2: 1 | H2: 1 | I2: 0 | J2: 26
A3: 1 | B3: There is most likely going to be fog around: | C3: 0 | D3: [14.75 4.90625 2.421875 3.6875 ] | E3: [9.9992657e-01 5.3073996e-05 4.4251851e-06 1.5688644e-05] | F3: 0 | G3: 1 | H3: 0.99993 | I3: 0 | J3: 14.75
A4: 2 | B4: Predators eat | C4: 2 | D4: [-0.11181641 -0.7421875 12.875 -0.29492188] | E4: [2.2903128e-06 1.2193493e-06 9.9999428e-01 1.9070985e-06] | F4: 2 | G4: 1 | H4: 0.99999 | I4: 0 | J4: 12.875
A5: 3 | B5: Oak tree seeds are planted and a sidewalk is paved right next to that spot, until eventually, the tree is tall and the roots must extend past the sidewalk, which means | C5: 2 | D5: [ 5.375 1.28125 18. 4.3125 ] | E5: [3.2887474e-06 5.4845053e-08 9.9999619e-01 1.1365606e-06] | F5: 2 | G5: 1 | H5: 1 | I5: 0 | J5: 18
A6: 4 | B6: An electric car runs on electricity via | C6: 2 | D6: [ 6.03125 9.125 19.25 5.4375 ] | E6: [1.8161495e-06 4.0063616e-05 9.9995804e-01 1.0029730e-06] | F6: 2 | G6: 1 | H6: 0.99996 | I6: 0 | J6: 19.25
A7: 5 | B7: As the rain forest is deforested the atmosphere will increase with | C7: 2 | D7: [ 2.734375 1.0390625 15.8125 2.3125 ] | E7: [2.0904549e-06 3.8368600e-07 9.9999619e-01 1.3709539e-06] | F7: 2 | G7: 1 | H7: 1 | I7: 0 | J7: 15.8125
A8: 6 | B8: an electric car contains a motor that runs on | C8: 2 | D8: [ 2.671875 1.875 16. 2.703125] | E8: [1.6280480e-06 7.3381869e-07 9.9999619e-01 1.6797278e-06] | F8: 2 | G8: 1 | H8: 1 | I8: 0 | J8: 16
A9: 7 | B9: The middle of the day usually involves the bright star nearest to the earth to be straight overhead why? | C9: 1 | D9: [12. 24.375 11.625 11.4375] | E9: [4.2228112e-06 9.9999046e-01 2.9022926e-06 2.4060853e-06] | F9: 1 | G9: 1 | H9: 0.99999 | I9: 0 | J9: 24.375
A10: 8 | B10: The summer solstice in the northern hemisphere is four months before | C10: 3 | D10: [13.5625 23.25 11.5625 15.25 ] | E10: [6.2029139e-05 9.9959379e-01 8.3947316e-06 3.3532636e-04] | F10: 1 | G10: 1 | H10: 0.99959 | I10: 1e-05 | J10: 23.25
A11: 9 | B11: The main component in dirt is | C11: 1 | D11: [ 4.625 17.125 3.546875 3.71875 ] | E11: [3.7266318e-06 9.9999428e-01 1.2679226e-06 1.5056954e-06] | F11: 1 | G11: 1 | H11: 0.99999 | I11: 0 | J11: 17.125
A12: 10 | B12: It's easier for human's to survive in: | C12: 2 | D12: [12.75 10.75 25.25 11.75] | E12: [3.7266318e-06 5.0434477e-07 9.9999428e-01 1.3709513e-06] | F12: 2 | G12: 1 | H12: 0.99999 | I12: 0 | J12: 25.25
A13: 11 | B13: A cactus stem is used to store | C13: 1 | D13: [ 3.890625 17.5 2.21875 2.96875 ] | E13: [1.2289174e-06 9.9999809e-01 2.3090675e-07 4.8882958e-07] | F13: 1 | G13: 1 | H13: 1 | I13: 0 | J13: 17.5
... A2501: 499 | B2501: Some animals use a liquid coming from their skin to adjust to | C2501: 2 | D2501: [16.625 13.875 25.375 15. ] | E2501: [1.5842960e-04 1.0128065e-05 9.9979973e-01 3.1196636e-05] | F2501: 2 | G2501: 5 | H2501: 0.9998 | I2501: 1e-05 | J2501: 25.375

Sheet combined_test_analysis
A1: idx | B1: input | C1: true_labels | D1: logits | E1: softmax_probs | F1: preds | G1: seed | H1: max_softmax_probs | I1: min_softmax_probs | J1: max_logits | K1: Predıctıon Status | L1: sk_logits | M1: sk_softmax_probs | N1: sk_preds | O1: sk_seed | P1: sk_max_softmax_probs | Q1: sk_min_softmax_probs | R1: sk_max_logits | S1: Predıctıon Status | T1: duo_softmax_probs | U1: duo_preds | V1: duo_max_softmax_probs | W1: Predıctıon Status
A2: =base_test!A2 -> 0 | B2: =base_test!B2 -> A person wants to start saving money so that they can afford a nice vacation at the end of the year. After looking over their budget and expenses, they decide the best way to save money is to | C2: =base_test!C2 -> 1 | D2: =base_test!D2 -> [12. 26. 12.3125 12. ] | E2: =base_test!E2 -> [8.3152713e-07 9.9999809e-01 1.1365628e-06 8.3152713e-07] | F2: =base_test!F2 -> 1 | G2: =base_test!G2 -> 1 | H2: =base_test!H2 -> 1 | ... J2: =base_test!J2 -> 26 | K2: =IF(F2=C2,"Correct","Incorrect") -> Correct | L2: =sidekick_test!D2 -> [ 9.8125 21.625 12.4375 9.6875] | M2: =sidekick_test!E2 -> [7.4104723e-06 9.9988365e-01 1.0229842e-04 6.5397189e-06] | N2: =sidekick_test!F2 -> 1 | O2: =sidekick_test!G2 -> 1 | P2: =sidekick_test!H2 -> 0.99988 | Q2: =sidekick_test!I2 -> 1e-05 | R2: =sidekick_test!J2 -> 21.625 | S2: =IF(N2=C2,"Correct","Incorrect") -> Correct | T2: =duo_test!D2 -> [2.58880882e-06 9.99983230e-01 1.17552423e-05 2.42613748e-06] | U2: =duo_test!E2 -> 1 | V2: =duo_test!G2 -> 0.99998 | W2: =IF(U2=C2,"Correct","Incorrect") -> Correct
A3: =base_test!A3 -> 1 | B3: =base_test!B3 -> There is most likely going to be fog around: | C3: =base_test!C3 -> 0 | D3: =base_test!D3 -> [14.75 4.90625 2.421875 3.6875 ] | E3: =base_test!E3 -> [9.9992657e-01 5.3073996e-05 4.4251851e-06 1.5688644e-05] | F3: =base_test!F3 -> 0 | G3: =base_test!G3 -> 1 | H3: =base_test!H3 -> 0.99993 | ... J3: =base_test!J3 -> 14.75 | K3: =IF(F3=C3,"Correct","Incorrect") -> Correct | L3: =sidekick_test!D3 -> [18.625 5.71875 5.0625 6.53125] | M3: =sidekick_test!E3 -> [9.9999046e-01 2.4824626e-06 1.2878846e-06 5.5943156e-06] | N3: =sidekick_test!F3 -> 0 | O3: =sidekick_test!G3 -> 1 | P3: =sidekick_test!H3 -> 0.99999 | Q3: =sidekick_test!I3 -> 0 | R3: =sidekick_test!J3 -> 18.625 | S3: =IF(N3=C3,"Correct","Incorrect") -> Correct | T3: =duo_test!D3 -> [9.99977660e-01 1.08238553e-05 2.33147622e-06 9.18512081e-06] | U3: =duo_test!E3 -> 0 | V3: =duo_test!G3 -> 0.99998 | W3: =IF(U3=C3,"Correct","Incorrect") -> Correct
A4: =base_test!A4 -> 2 | B4: =base_test!B4 -> Predators eat | C4: =base_test!C4 -> 2 | D4: =base_test!D4 -> [-0.11181641 -0.7421875 12.875 -0.29492188] | E4: =base_test!E4 -> [2.2903128e-06 1.2193493e-06 9.9999428e-01 1.9070985e-06] | F4: =base_test!F4 -> 2 | G4: =base_test!G4 -> 1 | H4: =base_test!H4 -> 0.99999 | ... J4: =base_test!J4 -> 12.875 | K4: =IF(F4=C4,"Correct","Incorrect") -> Correct | L4: =sidekick_test!D4 -> [ 5.53125 5.75 18.25 5.6875 ] | M4: =sidekick_test!E4 -> [2.9944215e-06 3.7266177e-06 9.9999046e-01 3.5008334e-06] | N4: =sidekick_test!F4 -> 2 | O4: =sidekick_test!G4 -> 1 | P4: =sidekick_test!H4 -> 0.99999 | Q4: =sidekick_test!I4 -> 0 | R4: =sidekick_test!J4 -> 18.25 | S4: =IF(N4=C4,"Correct","Incorrect") -> Correct | T4: =duo_test!D4 -> [2.63230839e-06 2.17784515e-06 9.99992576e-01 2.61415770e-06] | U4: =duo_test!E4 -> 2 | V4: =duo_test!G4 -> 0.99999 | W4: =IF(U4=C4,"Correct","Incorrect") -> Correct
A5: =base_test!A5 -> 3 | B5: =base_test!B5 -> Oak tree seeds are planted and a sidewalk is paved right next to that spot, until eventually, the tree is tall and the roots must extend past the sidewalk, which means | C5: =base_test!C5 -> 2 | D5: =base_test!D5 -> [ 5.375 1.28125 18. 4.3125 ] | E5: =base_test!E5 -> [3.2887474e-06 5.4845053e-08 9.9999619e-01 1.1365606e-06] | F5: =base_test!F5 -> 2 | G5: =base_test!G5 -> 1 | H5: =base_test!H5 -> 1 | ... J5: =base_test!J5 -> 18 | K5: =IF(F5=C5,"Correct","Incorrect") -> Correct | L5: =sidekick_test!D5 -> [ 9. 8.25 20. 8.3125] | M5: =sidekick_test!E5 -> [1.6701159e-05 7.8890689e-06 9.9996758e-01 8.3978703e-06] | N5: =sidekick_test!F5 -> 2 | O5: =sidekick_test!G5 -> 1 | P5: =sidekick_test!H5 -> 0.99997 | Q5: =sidekick_test!I5 -> 1e-05 | R5: =sidekick_test!J5 -> 20 | S5: =IF(N5=C5,"Correct","Incorrect") -> Correct | T5: =duo_test!D5 -> [7.64586407e-06 7.23553814e-07 9.99988420e-01 3.21027622e-06] | U5: =duo_test!E5 -> 2 | V5: =duo_test!G5 -> 0.99999 | W5: =IF(U5=C5,"Correct","Incorrect") -> Correct
A6: =base_test!A6 -> 4 | B6: =base_test!B6 -> An electric car runs on electricity via | C6: =base_test!C6 -> 2 | D6: =base_test!D6 -> [ 6.03125 9.125 19.25 5.4375 ] | E6: =base_test!E6 -> [1.8161495e-06 4.0063616e-05 9.9995804e-01 1.0029730e-06] | F6: =base_test!F6 -> 2 | G6: =base_test!G6 -> 1 | H6: =base_test!H6 -> 0.99996 | ... J6: =base_test!J6 -> 19.25 | K6: =IF(F6=C6,"Correct","Incorrect") -> Correct | L6: =sidekick_test!D6 -> [ 8.5 13.4375 10.9375 9.0625] | M6: =sidekick_test!E6 -> [0.00650954 0.90756804 0.07449772 0.0114246 ] | N6: =sidekick_test!F6 -> 1 | O6: =sidekick_test!G6 -> 1 | P6: =sidekick_test!H6 -> 0.90757 | Q6: =sidekick_test!I6 -> 0.00651 | R6: =sidekick_test!J6 -> 13.4375 | S6: =IF(N6=C6,"Correct","Incorrect") -> Incorrect | T6: =duo_test!D6 -> [4.76013776e-04 2.73489408e-02 9.71695903e-01 4.79142245e-04] | U6: =duo_test!E6 -> 2 | V6: =duo_test!G6 -> 0.9717 | W6: =IF(U6=C6,"Correct","Incorrect") -> Correct
A7: =base_test!A7 -> 5 | B7: =base_test!B7 -> As the rain forest is deforested the atmosphere will increase with | C7: =base_test!C7 -> 2 | D7: =base_test!D7 -> [ 2.734375 1.0390625 15.8125 2.3125 ] | E7: =base_test!E7 -> [2.0904549e-06 3.8368600e-07 9.9999619e-01 1.3709539e-06] | F7: =base_test!F7 -> 2 | G7: =base_test!G7 -> 1 | H7: =base_test!H7 -> 1 | ... J7: =base_test!J7 -> 15.8125 | K7: =IF(F7=C7,"Correct","Incorrect") -> Correct | L7: =sidekick_test!D7 -> [ 6.0625 6.40625 16.875 6.4375 ] | M7: =sidekick_test!E7 -> [2.0144522e-05 2.8408329e-05 9.9992180e-01 2.9310106e-05] | N7: =sidekick_test!F7 -> 2 | O7: =sidekick_test!G7 -> 1 | P7: =sidekick_test!H7 -> 0.99992 | Q7: =sidekick_test!I7 -> 2e-05 | R7: =sidekick_test!J7 -> 16.875 | S7: =IF(N7=C7,"Correct","Incorrect") -> Correct | T7: =duo_test!D7 -> [6.77767009e-06 3.58572015e-06 9.99982914e-01 6.72262811e-06] | U7: =duo_test!E7 -> 2 | V7: =duo_test!G7 -> 0.99998 | W7: =IF(U7=C7,"Correct","Incorrect") -> Correct
A8: =base_test!A8 -> 6 | B8: =base_test!B8 -> an electric car contains a motor that runs on | C8: =base_test!C8 -> 2 | D8: =base_test!D8 -> [ 2.671875 1.875 16. 2.703125] | E8: =base_test!E8 -> [1.6280480e-06 7.3381869e-07 9.9999619e-01 1.6797278e-06] | F8: =base_test!F8 -> 2 | G8: =base_test!G8 -> 1 | H8: =base_test!H8 -> 1 | ... J8: =base_test!J8 -> 16 | K8: =IF(F8=C8,"Correct","Incorrect") -> Correct | L8: =sidekick_test!D8 -> [ 7.09375 14.625 9.375 6.78125] | M8: =sidekick_test!E8 -> [5.3277734e-04 9.9386197e-01 5.2153091e-03 3.8978824e-04] | N8: =sidekick_test!F8 -> 1 | O8: =sidekick_test!G8 -> 1 | P8: =sidekick_test!H8 -> 0.99386 | Q8: =sidekick_test!I8 -> 0.00039 | R8: =sidekick_test!J8 -> 14.625 | S8: =IF(N8=C8,"Correct","Incorrect") -> Incorrect | T8: =duo_test!D8 -> [4.95103171e-04 1.68428042e-02 9.82234766e-01 4.27326511e-04] | U8: =duo_test!E8 -> 2 | V8: =duo_test!G8 -> 0.98223 | W8: =IF(U8=C8,"Correct","Incorrect") -> Correct
A9: =base_test!A9 -> 7 | B9: =base_test!B9 -> The middle of the day usually involves the bright star nearest to the earth to be straight overhead why? | C9: =base_test!C9 -> 1 | D9: =base_test!D9 -> [12. 24.375 11.625 11.4375] | E9: =base_test!E9 -> [4.2228112e-06 9.9999046e-01 2.9022926e-06 2.4060853e-06] | F9: =base_test!F9 -> 1 | G9: =base_test!G9 -> 1 | H9: =base_test!H9 -> 0.99999 | ... J9: =base_test!J9 -> 24.375 | K9: =IF(F9=C9,"Correct","Incorrect") -> Correct | L9: =sidekick_test!D9 -> [ 9.125 20.75 10. 8.4375] | M9: =sidekick_test!E9 -> [8.9394689e-06 9.9996567e-01 2.1444672e-05 4.4950475e-06] | N9: =sidekick_test!F9 -> 1 | O9: =sidekick_test!G9 -> 1 | P9: =sidekick_test!H9 -> 0.99997 | Q9: =sidekick_test!I9 -> 0 | R9: =sidekick_test!J9 -> 20.75 | S9: =IF(N9=C9,"Correct","Incorrect") -> Correct | T9: =duo_test!D9 -> [6.23312025e-06 9.99982241e-01 8.19767685e-06 3.32835995e-06] | U9: =duo_test!E9 -> 1 | V9: =duo_test!G9 -> 0.99998 | W9: =IF(U9=C9,"Correct","Incorrect") -> Correct
A10: =base_test!A10 -> 8 | B10: =base_test!B10 -> The summer solstice in the northern hemisphere is four months before | C10: =base_test!C10 -> 3 | D10: =base_test!D10 -> [13.5625 23.25 11.5625 15.25 ] | E10: =base_test!E10 -> [6.2029139e-05 9.9959379e-01 8.3947316e-06 3.3532636e-04] | F10: =base_test!F10 -> 1 | G10: =base_test!G10 -> 1 | H10: =base_test!H10 -> 0.99959 | ... J10: =base_test!J10 -> 23.25 | K10: =IF(F10=C10,"Correct","Incorrect") -> Incorrect | L10: =sidekick_test!D10 -> [14.125 13.75 18.875 13.9375] | M10: =sidekick_test!E10 -> [0.00846737 0.00581953 0.9786944 0.00701969] | N10: =sidekick_test!F10 -> 2 | O10: =sidekick_test!G10 -> 1 | P10: =sidekick_test!H10 -> 0.97869 | Q10: =sidekick_test!I10 -> 0.00582 | R10: =sidekick_test!J10 -> 18.875 | S10: =IF(N10=C10,"Correct","Incorrect") -> Incorrect | T10: =duo_test!D10 -> [0.01060288 0.9200125 0.04773115 0.02165346] | U10: =duo_test!E10 -> 1 | V10: =duo_test!G10 -> 0.92001 | W10: =IF(U10=C10,"Correct","Incorrect") -> Incorrect
A11: =base_test!A11 -> 9 | B11: =base_test!B11 -> The main component in dirt is | C11: =base_test!C11 -> 1 | D11: =base_test!D11 -> [ 4.625 17.125 3.546875 3.71875 ] | E11: =base_test!E11 -> [3.7266318e-06 9.9999428e-01 1.2679226e-06 1.5056954e-06] | F11: =base_test!F11 -> 1 | G11: =base_test!G11 -> 1 | H11: =base_test!H11 -> 0.99999 | ... J11: =base_test!J11 -> 17.125 | K11: =IF(F11=C11,"Correct","Incorrect") -> Correct | L11: =sidekick_test!D11 -> [ 7.78125 18.875 7.71875 7.1875 ] | M11: =sidekick_test!E11 -> [1.5206491e-05 9.9996185e-01 1.4285177e-05 8.3978221e-06] | N11: =sidekick_test!F11 -> 1 | O11: =sidekick_test!G11 -> 1 | P11: =sidekick_test!H11 -> 0.99996 | Q11: =sidekick_test!I11 -> 1e-05 | R11: =sidekick_test!J11 -> 18.875 | S11: =IF(N11=C11,"Correct","Incorrect") -> Correct | T11: =duo_test!D11 -> [7.73372134e-06 9.99984133e-01 4.45825011e-06 3.67511197e-06] | U11: =duo_test!E11 -> 1 | V11: =duo_test!G11 -> 0.99998 | W11: =IF(U11=C11,"Correct","Incorrect") -> Correct
A12: =base_test!A12 -> 10 | B12: =base_test!B12 -> It's easier for human's to survive in: | C12: =base_test!C12 -> 2 | D12: =base_test!D12 -> [12.75 10.75 25.25 11.75] | E12: =base_test!E12 -> [3.7266318e-06 5.0434477e-07 9.9999428e-01 1.3709513e-06] | F12: =base_test!F12 -> 2 | G12: =base_test!G12 -> 1 | H12: =base_test!H12 -> 0.99999 | ... J12: =base_test!J12 -> 25.25 | K12: =IF(F12=C12,"Correct","Incorrect") -> Correct | L12: =sidekick_test!D12 -> [10.4375 10.8125 19.875 11.25 ] | M12: =sidekick_test!E12 -> [7.9649428e-05 1.1588923e-04 9.9962431e-01 1.7949275e-04] | N12: =sidekick_test!F12 -> 2 | O12: =sidekick_test!G12 -> 1 | P12: =sidekick_test!H12 -> 0.99962 | Q12: =sidekick_test!I12 -> 8e-05 | R12: =sidekick_test!J12 -> 19.875 | S12: =IF(N12=C12,"Correct","Incorrect") -> Correct | T12: =duo_test!D12 -> [1.82735062e-05 8.48671835e-06 9.99956013e-01 1.72267637e-05] | U12: =duo_test!E12 -> 2 | V12: =duo_test!G12 -> 0.99996 | W12: =IF(U12=C12,"Correct","Incorrect") -> Correct
A13: =base_test!A13 -> 11 | B13: =base_test!B13 -> A cactus stem is used to store | C13: =base_test!C13 -> 1 | D13: =base_test!D13 -> [ 3.890625 17.5 2.21875 2.96875 ] | E13: =base_test!E13 -> [1.2289174e-06 9.9999809e-01 2.3090675e-07 4.8882958e-07] | F13: =base_test!F13 -> 1 | G13: =base_test!G13 -> 1 | H13: =base_test!H13 -> 1 | ... J13: =base_test!J13 -> 17.5 | K13: =IF(F13=C13,"Correct","Incorrect") -> Correct | L13: =sidekick_test!D13 -> [ 8.4375 19.5 9.5 9.625 ] | M13: =sidekick_test!E13 -> [1.5688031e-05 9.9988747e-01 4.5394820e-05 5.1439070e-05] | N13: =sidekick_test!F13 -> 1 | O13: =sidekick_test!G13 -> 1 | P13: =sidekick_test!H13 -> 0.99989 | Q13: =sidekick_test!I13 -> 2e-05 | R13: =sidekick_test!J13 -> 19.5 | S13: =IF(N13=C13,"Correct","Incorrect") -> Correct | T13: =duo_test!D13 -> [4.61082086e-06 9.99986323e-01 3.58285864e-06 5.48311905e-06] | U13: =duo_test!E13 -> 1 | V13: =duo_test!G13 -> 0.99999 | W13: =IF(U13=C13,"Correct","Incorrect") -> Correct
... A2501: =base_test!A2501 -> 499 | B2501: =base_test!B2501 -> Some animals use a liquid coming from their skin to adjust to | C2501: =base_test!C2501 -> 2 | D2501: =base_test!D2501 -> [16.625 13.875 25.375 15. ] | E2501: =base_test!E2501 -> [1.5842960e-04 1.0128065e-05 9.9979973e-01 3.1196636e-05] | F2501: =base_test!F2501 -> 2 | G2501: =base_test!G2501 -> 5 | H2501: =base_test!H2501 -> 0.9998 | ... J2501: =base_test!J2501 -> 25.375 | K2501: =IF(F2501=C2501,"Correct","Incorrect") -> Correct | L2501: =sidekick_test!D2501 -> [16.75 9.375 11.0625 10.8125] | M2501: =sidekick_test!E2501 -> [9.9339008e-01 6.2258408e-04 3.3656578e-03 2.6211769e-03] | N2501: =sidekick_test!F2501 -> 0 | O2501: =sidekick_test!G2501 -> 5 | P2501: =sidekick_test!H2501 -> 0.99339 | Q2501: =sidekick_test!I2501 -> 0.00062 | R2501: =sidekick_test!J2501 -> 16.75 | S2501: =IF(N2501=C2501,"Correct","Incorrect") -> Incorrect | T2501: =duo_test!D2501 -> [0.23497618 0.0013258 0.75888639 0.00481163] | U2501: =duo_test!E2501 -> 2 | V2501: =duo_test!G2501 -> 0.75889 | W2501: =IF(U2501=C2501,"Correct","Incorrect") -> Correct

Sheet combined_val_analysis
A1: idx | B1: input | C1: true_labels | D1: logits | E1: softmax_probs | F1: preds | G1: seed | H1: max_softmax_probs | I1: min_softmax_probs | J1: max_logits | K1: Predıctıon Status | L1: sk_logits | M1: sk_softmax_probs | N1: sk_preds | O1: sk_seed | P1: sk_max_softmax_probs | Q1: sk_min_softmax_probs | R1: sk_max_logits | S1: Predıctıon Status | T1: duo_softmax_probs | U1: duo_preds | V1: duo_max_softmax_probs | W1: Predıctıon Status
A2: =base_val!A2 -> 0 | B2: =base_val!B2 -> Frilled sharks and angler fish live far beneath the surface of the ocean, which is why they are known as | C2: =base_val!C2 -> 0 | D2: =base_val!D2 -> [19.875 5.75 6.40625 7.28125] | E2: =base_val!E2 -> [9.9999428e-01 7.3381733e-07 1.4144699e-06 3.3931369e-06] | F2: =base_val!F2 -> 0 | G2: =base_val!G2 -> 1 | H2: =base_val!H2 -> 0.99999 | ... J2: =base_val!J2 -> 19.875 | K2: =IF(F2=C2,"Correct","Incorrect") -> Correct | L2: =sidekick_val!D2 -> [15.6875 6.875 6.09375 7. ] | M2: =sidekick_val!E2 -> [9.9961478e-01 1.4880330e-04 6.8127112e-05 1.6861623e-04] | N2: =sidekick_val!F2 -> 0 | O2: =sidekick_val!G2 -> 1 | P2: =sidekick_val!H2 -> 0.99961 | Q2: =sidekick_val!I2 -> 7e-05 | R2: =sidekick_val!J2 -> 15.6875 | S2: =IF(N2=C2,"Correct","Incorrect") -> Correct | T2: =duo_val!D2 -> [9.99952068e-01 1.15721468e-05 1.05754075e-05 2.57840376e-05] | U2: =duo_val!E2 -> 0 | V2: =duo_val!G2 -> 0.99995 | W2: =IF(U2=C2,"Correct","Incorrect") -> Correct
A3: =base_val!A3 -> 1 | B3: =base_val!B3 -> Gas can fill any container it is given, and liquid | C3: =base_val!C3 -> 3 | D3: =base_val!D3 -> [ 3.640625 -1.96875 1.96875 16.625 ] | E3: =base_val!E3 -> [2.295920e-06 8.410778e-09 4.313906e-07 9.999981e-01] | F3: =base_val!F3 -> 3 | G3: =base_val!G3 -> 1 | H3: =base_val!H3 -> 1 | ... J3: =base_val!J3 -> 16.625 | K3: =IF(F3=C3,"Correct","Incorrect") -> Correct | L3: =sidekick_val!D3 -> [ 5.21875 4.96875 4.84375 15.8125 ] | M3: =sidekick_val!E3 -> [2.5070669e-05 1.9525056e-05 1.7230801e-05 9.9993801e-01] | N3: =sidekick_val!F3 -> 3 | O3: =sidekick_val!G3 -> 1 | P3: =sidekick_val!H3 -> 0.99994 | Q3: =sidekick_val!I3 -> 2e-05 | R3: =sidekick_val!J3 -> 15.8125 | S3: =IF(N3=C3,"Correct","Incorrect") -> Correct | T3: =duo_val!D3 -> [7.94296412e-06 4.70192302e-07 2.92625014e-06 9.99988661e-01] | U3: =duo_val!E3 -> 3 | V3: =duo_val!G3 -> 0.99999 | W3: =IF(U3=C3,"Correct","Incorrect") -> Correct
A4: =base_val!A4 -> 2 | B4: =base_val!B4 -> When birds migrate south for the winter, they do it because | C4: =base_val!C4 -> 0 | D4: =base_val!D4 -> [26. 15. 14.375 13.625] | E4: =base_val!E4 -> [9.9996948e-01 1.6701191e-05 8.9395035e-06 4.2227225e-06] | F4: =base_val!F4 -> 0 | G4: =base_val!G4 -> 1 | H4: =base_val!H4 -> 0.99997 | ... J4: =base_val!J4 -> 26 | K4: =IF(F4=C4,"Correct","Incorrect") -> Correct | L4: =sidekick_val!D4 -> [19.25 11.0625 12.0625 12.6875] | M4: =sidekick_val!E4 -> [9.9755967e-01 2.7742962e-04 7.5413188e-04 1.4089039e-03] | N4: =sidekick_val!F4 -> 0 | O4: =sidekick_val!G4 -> 1 | P4: =sidekick_val!H4 -> 0.99756 | Q4: =sidekick_val!I4 -> 0.00028 | R4: =sidekick_val!J4 -> 19.25 | S4: =IF(N4=C4,"Correct","Incorrect") -> Correct | T4: =duo_val!D4 -> [9.99752284e-01 7.19127627e-05 8.94893508e-05 8.63139095e-05] | U4: =duo_val!E4 -> 0 | V4: =duo_val!G4 -> 0.99975 | W4: =IF(U4=C4,"Correct","Incorrect") -> Correct
A5: =base_val!A5 -> 3 | B5: =base_val!B5 -> If a person walks in the opposite direction of a compass arrow they are walking | C5: =base_val!C5 -> 3 | D5: =base_val!D5 -> [11. 4.09375 1.484375 0.79296875] | E5: =base_val!E5 -> [9.9888957e-01 1.0003943e-03 7.3609532e-05 3.6868896e-05] | F5: =base_val!F5 -> 0 | G5: =base_val!G5 -> 1 | H5: =base_val!H5 -> 0.99889 | ... J5: =base_val!J5 -> 11 | K5: =IF(F5=C5,"Correct","Incorrect") -> Incorrect | L5: =sidekick_val!D5 -> [ 7.71875 6.84375 7.03125 11.5 ] | M5: =sidekick_val!E5 -> [0.02183857 0.00910367 0.01098112 0.95807654] | N5: =sidekick_val!F5 -> 3 | O5: =sidekick_val!G5 -> 1 | P5: =sidekick_val!H5 -> 0.95808 | Q5: =sidekick_val!I5 -> 0.0091 | R5: =sidekick_val!J5 -> 11.5 | S5: =IF(N5=C5,"Correct","Incorrect") -> Correct | T5: =duo_val!D5 -> [0.92355624 0.02118472 0.0066591 0.04859994] | U5: =duo_val!E5 -> 0 | V5: =duo_val!G5 -> 0.92356 | W5: =IF(U5=C5,"Correct","Incorrect") -> Incorrect
A6: =base_val!A6 -> 4 | B6: =base_val!B6 -> An example of lots kinetic energy would be | C6: =base_val!C6 -> 3 | D6: =base_val!D6 -> [ 6.875 3. 2.65625 19.125 ] | E6: =base_val!E6 -> [4.785090e-06 9.931137e-08 7.042231e-08 9.999943e-01] | F6: =base_val!F6 -> 3 | G6: =base_val!G6 -> 1 | H6: =base_val!H6 -> 0.99999 | ... J6: =base_val!J6 -> 19.125 | K6: =IF(F6=C6,"Correct","Incorrect") -> Correct | L6: =sidekick_val!D6 -> [ 2.984375 2.4375 -0.9296875 13.8125 ] | M6: =sidekick_val!E6 -> [1.9833136e-05 1.1478539e-05 3.9585456e-07 9.9996853e-01] | N6: =sidekick_val!F6 -> 3 | O6: =sidekick_val!G6 -> 1 | P6: =sidekick_val!H6 -> 0.99997 | Q6: =sidekick_val!I6 -> 0 | R6: =sidekick_val!J6 -> 13.8125 | S6: =IF(N6=C6,"Correct","Incorrect") -> Correct | T6: =duo_val!D6 -> [1.00112238e-05 1.16952708e-06 1.72586659e-07 9.99988647e-01] | U6: =duo_val!E6 -> 3 | V6: =duo_val!G6 -> 0.99999 | W6: =IF(U6=C6,"Correct","Incorrect") -> Correct
A7: =base_val!A7 -> 5 | B7: =base_val!B7 -> Which organism cannot specialize? | C7: =base_val!C7 -> 3 | D7: =base_val!D7 -> [ 2.859375 -0.55078125 1.0546875 14.125 ] | E7: =base_val!E7 -> [1.2805443e-05 4.2304109e-07 2.1068265e-06 9.9998474e-01] | F7: =base_val!F7 -> 3 | G7: =base_val!G7 -> 1 | H7: =base_val!H7 -> 0.99998 | ... J7: =base_val!J7 -> 14.125 | K7: =IF(F7=C7,"Correct","Incorrect") -> Correct | L7: =sidekick_val!D7 -> [ 6.625 6.5 6.25 17.5 ] | M7: =sidekick_val!E7 -> [1.8924604e-05 1.6700904e-05 1.3006677e-05 9.9995232e-01] | N7: =sidekick_val!F7 -> 3 | O7: =sidekick_val!G7 -> 1 | P7: =sidekick_val!H7 -> 0.99995 | Q7: =sidekick_val!I7 -> 1e-05 | R7: =sidekick_val!J7 -> 17.5 | S7: =IF(N7=C7,"Correct","Incorrect") -> Correct | T7: =duo_val!D7 -> [1.56843892e-05 2.85220903e-06 5.42079307e-06 9.99976043e-01] | U7: =duo_val!E7 -> 3 | V7: =duo_val!G7 -> 0.99998 | W7: =IF(U7=C7,"Correct","Incorrect") -> Correct
A8: =base_val!A8 -> 6 | B8: =base_val!B8 -> A person can grow cabbage in January with the help of what product? | C8: =base_val!C8 -> 0 | D8: =base_val!D8 -> [18.125 5.90625 5.0625 5.71875] | E8: =base_val!E8 -> [9.9998856e-01 4.9369569e-06 2.1233586e-06 4.0928808e-06] | F8: =base_val!F8 -> 0 | G8: =base_val!G8 -> 1 | H8: =base_val!H8 -> 0.99999 | ... J8: =base_val!J8 -> 18.125 | K8: =IF(F8=C8,"Correct","Incorrect") -> Correct | L8: =sidekick_val!D8 -> [18.625 7.375 6.6875 7.1875] | M8: =sidekick_val!E8 -> [9.9996948e-01 1.3006901e-05 6.5402805e-06 1.0783099e-05] | N8: =sidekick_val!F8 -> 0 | O8: =sidekick_val!G8 -> 1 | P8: =sidekick_val!H8 -> 0.99997 | Q8: =sidekick_val!I8 -> 1e-05 | R8: =sidekick_val!J8 -> 18.625 | S8: =IF(N8=C8,"Correct","Incorrect") -> Correct | T8: =duo_val!D8 -> [9.99981261e-01 8.16369166e-06 3.80786321e-06 6.76793810e-06] | U8: =duo_val!E8 -> 0 | V8: =duo_val!G8 -> 0.99998 | W8: =IF(U8=C8,"Correct","Incorrect") -> Correct
A9: =base_val!A9 -> 7 | B9: =base_val!B9 -> A frog, in winter, will burrow itself into soft mud, until it freezes, then in the spring | C9: =base_val!C9 -> 1 | D9: =base_val!D9 -> [13.375 26. 11.0625 12.4375] | E9: =base_val!E9 -> [3.2887410e-06 9.9999428e-01 3.2562946e-07 1.2878895e-06] | F9: =base_val!F9 -> 1 | G9: =base_val!G9 -> 1 | H9: =base_val!H9 -> 0.99999 | ... J9: =base_val!J9 -> 26 | K9: =IF(F9=C9,"Correct","Incorrect") -> Correct | L9: =sidekick_val!D9 -> [ 9.875 20.125 10.75 9.75 ] | M9: =sidekick_val!E9 -> [3.5352172e-05 9.9984932e-01 8.4805455e-05 3.1198182e-05] | N9: =sidekick_val!F9 -> 1 | O9: =sidekick_val!G9 -> 1 | P9: =sidekick_val!H9 -> 0.99985 | Q9: =sidekick_val!I9 -> 3e-05 | R9: =sidekick_val!J9 -> 20.125 | S9: =IF(N9=C9,"Correct","Incorrect") -> Correct | T9: =duo_val!D9 -> [1.12857043e-05 9.99976129e-01 5.84694841e-06 6.73871838e-06] | U9: =duo_val!E9 -> 1 | V9: =duo_val!G9 -> 0.99998 | W9: =IF(U9=C9,"Correct","Incorrect") -> Correct
A10: =base_val!A10 -> 8 | B10: =base_val!B10 -> Which describes the size of an object? | C10: =base_val!C10 -> 3 | D10: =base_val!D10 -> [12.625 9.0625 9.3125 24.625 ] | E10: =base_val!E10 -> [6.1441774e-06 1.7429689e-07 2.2380164e-07 9.9999428e-01] | F10: =base_val!F10 -> 3 | G10: =base_val!G10 -> 1 | H10: =base_val!H10 -> 0.99999 | ... J10: =base_val!J10 -> 24.625 | K10: =IF(F10=C10,"Correct","Incorrect") -> Correct | L10: =sidekick_val!D10 -> [ 9.4375 10.0625 9.6875 21.375 ] | M10: =sidekick_val!E10 -> [6.5403055e-06 1.2218899e-05 8.3979185e-06 9.9997330e-01] | N10: =sidekick_val!F10 -> 3 | O10: =sidekick_val!G10 -> 1 | P10: =sidekick_val!H10 -> 0.99997 | Q10: =sidekick_val!I10 -> 1e-05 | R10: =sidekick_val!J10 -> 21.375 | S10: =IF(N10=C10,"Correct","Incorrect") -> Correct | T10: =duo_val!D10 -> [6.34679427e-06 1.58330101e-06 1.46965112e-06 9.99990600e-01] | U10: =duo_val!E10 -> 3 | V10: =duo_val!G10 -> 0.99999 | W10: =IF(U10=C10,"Correct","Incorrect") -> Correct
A11: =base_val!A11 -> 9 | B11: =base_val!B11 -> A body may find its temperature to be lowered after | C11: =base_val!C11 -> 1 | D11: =base_val!D11 -> [ 3.546875 17.125 2.265625 1.4453125] | E11: =base_val!E11 -> [1.2679275e-06 9.9999809e-01 3.5209075e-07 1.5502346e-07] | F11: =base_val!F11 -> 1 | G11: =base_val!G11 -> 1 | H11: =base_val!H11 -> 1 | ... J11: =base_val!J11 -> 17.125 | K11: =IF(F11=C11,"Correct","Incorrect") -> Correct | L11: =sidekick_val!D11 -> [ 6.375 16.625 8.75 8.625] | M11: =sidekick_val!E11 -> [3.533094e-05 9.992488e-01 3.798434e-04 3.352106e-04] | N11: =sidekick_val!F11 -> 1 | O11: =sidekick_val!G11 -> 1 | P11: =sidekick_val!H11 -> 0.99925 | Q11: =sidekick_val!I11 -> 4e-05 | R11: =sidekick_val!J11 -> 16.625 | S11: =IF(N11=C11,"Correct","Incorrect") -> Correct | T11: =duo_val!D11 -> [7.13669265e-06 9.99971281e-01 1.32268345e-05 8.35555704e-06] | U11: =duo_val!E11 -> 1 | V11: =duo_val!G11 -> 0.99997 | W11: =IF(U11=C11,"Correct","Incorrect") -> Correct
A12: =base_val!A12 -> 10 | B12: =base_val!B12 -> If a person enjoys long, sunny days their favorite month would be | C12: =base_val!C12 -> 1 | D12: =base_val!D12 -> [ 3.953125 17.25 1.78125 2.765625] | E12: =base_val!E12 -> [1.6797310e-06 9.9999809e-01 1.9142841e-07 5.1228903e-07] | F12: =base_val!F12 -> 1 | G12: =base_val!G12 -> 1 | H12: =base_val!H12 -> 1 | ... J12: =base_val!J12 -> 17.25 | K12: =IF(F12=C12,"Correct","Incorrect") -> Correct | L12: =sidekick_val!D12 -> [ 4.15625 16.75 7.25 6.15625] | M12: =sidekick_val!E12 -> [3.3928068e-06 9.9989700e-01 7.4844123e-05 2.5069639e-05] | N12: =sidekick_val!F12 -> 1 | O12: =sidekick_val!G12 -> 1 | P12: =sidekick_val!H12 -> 0.9999 | Q12: =sidekick_val!I12 -> 0 | R12: =sidekick_val!J12 -> 16.75 | S12: =IF(N12=C12,"Correct","Incorrect") -> Correct | T12: =duo_val!D12 -> [2.41977066e-06 9.99989474e-01 4.24439675e-06 3.86150050e-06] | U12: =duo_val!E12 -> 1 | V12: =duo_val!G12 -> 0.99999 | W12: =IF(U12=C12,"Correct","Incorrect") -> Correct
A13: =base_val!A13 -> 11 | B13: =base_val!B13 -> An example of data collection is | C13: =base_val!C13 -> 2 | D13: =base_val!D13 -> [ 4.28125 1.5078125 18.5 3.21875 ] | E13: =base_val!E13 -> [6.6815210e-07 4.1724075e-08 1.0000000e+00 2.3090719e-07] | F13: =base_val!F13 -> 2 | G13: =base_val!G13 -> 1 | H13: =base_val!H13 -> 1 | ... J13: =base_val!J13 -> 18.5 | K13: =IF(F13=C13,"Correct","Incorrect") -> Correct | L13: =sidekick_val!D13 -> [ 5.71875 6.625 18.375 6.09375] | M13: =sidekick_val!E13 -> [3.1875268e-06 7.8892044e-06 9.9998474e-01 4.6378241e-06] | N13: =sidekick_val!F13 -> 2 | O13: =sidekick_val!G13 -> 1 | P13: =sidekick_val!H13 -> 0.99998 | Q13: =sidekick_val!I13 -> 0 | R13: =sidekick_val!J13 -> 18.375 | S13: =IF(N13=C13,"Correct","Incorrect") -> Correct | T13: =duo_val!D13 -> [1.50376884e-06 6.34418466e-07 9.99996766e-01 1.09613936e-06] | U13: =duo_val!E13 -> 2 | V13: =duo_val!G13 -> 1 | W13: =IF(U13=C13,"Correct","Incorrect") -> Correct
... A2501: =base_val!A2501 -> 499 | B2501: =base_val!B2501 -> Owls spend their nights | C2501: =base_val!C2501 -> 2 | D2501: =base_val!D2501 -> [12.9375 11.5 26.875 12.0625] | E2501: =base_val!E2501 -> [8.8515600e-07 2.1024299e-07 9.9999809e-01 3.6898794e-07] | F2501: =base_val!F2501 -> 2 | G2501: =base_val!G2501 -> 5 | H2501: =base_val!H2501 -> 1 | ... J2501: =base_val!J2501 -> 26.875 | K2501: =IF(F2501=C2501,"Correct","Incorrect") -> Correct | L2501: =sidekick_val!D2501 -> [ 5.75 6.0625 18. 5.21875] | M2501: =sidekick_val!E2501 -> [4.7850535e-06 6.5403929e-06 9.9998665e-01 2.8129878e-06] | N2501: =sidekick_val!F2501 -> 2 | O2501: =sidekick_val!G2501 -> 5 | P2501: =sidekick_val!H2501 -> 0.99999 | Q2501: =sidekick_val!I2501 -> 0 | R2501: =sidekick_val!J2501 -> 18 | S2501: =IF(N2501=C2501,"Correct","Incorrect") -> Correct | T2501: =duo_val!D2501 -> [2.14620961e-06 1.27724341e-06 9.99995505e-01 1.07156814e-06] | U2501: =duo_val!E2501 -> 2 | V2501: =duo_val!G2501 -> 1 | W2501: =IF(U2501=C2501,"Correct","Incorrect") -> Correct
